Utils03/__init__.py
Utils03/dlLib.py
utils03-0.2.0.dist-info/METADATA
utils03-0.2.0.dist-info/WHEEL
utils03-0.2.0.dist-info/top_level.txt
utils03-0.2.0.dist-info/RECORD
