Metadata-Version: 2.4
Name: Utils03
Version: 0.2.0
Summary: An library that contains a lot of utilities
Author-email: Reyzer <reyzervt@gmail.com>
License: MIT
Requires-Dist: requests
